MANIFEST.in
README.md
setup.cfg
setup.py
cellxgene.egg-info/PKG-INFO
cellxgene.egg-info/SOURCES.txt
cellxgene.egg-info/dependency_links.txt
cellxgene.egg-info/entry_points.txt
cellxgene.egg-info/not-zip-safe
cellxgene.egg-info/requires.txt
cellxgene.egg-info/top_level.txt
server/__init__.py
server/__main__.py
server/default_config.py
server/requirements-annotate.txt
server/requirements-prepare.txt
server/requirements.txt
server/annotate/__init__.py
server/annotate/annotation_types.py
server/app/__init__.py
server/app/app.py
server/app/session.py
server/cli/__init__.py
server/cli/annotate.py
server/cli/cli.py
server/cli/launch.py
server/cli/prepare.py
server/cli/upgrade.py
server/common/__init__.py
server/common/colors.py
server/common/constants.py
server/common/corpora.py
server/common/errors.py
server/common/genesets.py
server/common/health.py
server/common/rest.py
server/common/annotations/__init__.py
server/common/annotations/annotations.py
server/common/annotations/local_file_csv.py
server/common/compute/__init__.py
server/common/compute/diffexp_generic.py
server/common/compute/estimate_distribution.py
server/common/config/__init__.py
server/common/config/app_config.py
server/common/config/base_config.py
server/common/config/client_config.py
server/common/config/dataset_config.py
server/common/config/external_config.py
server/common/config/server_config.py
server/common/fbs/__init__.py
server/common/fbs/matrix.py
server/common/fbs/NetEncoding/Column.py
server/common/fbs/NetEncoding/Float32Array.py
server/common/fbs/NetEncoding/Float64Array.py
server/common/fbs/NetEncoding/Int32Array.py
server/common/fbs/NetEncoding/JSONEncodedArray.py
server/common/fbs/NetEncoding/Matrix.py
server/common/fbs/NetEncoding/TypedArray.py
server/common/fbs/NetEncoding/Uint32Array.py
server/common/fbs/NetEncoding/__init__.py
server/common/utils/__init__.py
server/common/utils/corpora_constants.py
server/common/utils/data_locator.py
server/common/utils/type_conversion_utils.py
server/common/utils/utils.py
server/common/web/__init__.py
server/common/web/static/main-1d9b57a05a93155621b5.js
server/common/web/static/main-1d9b57a05a93155621b5.js.LICENSE.txt
server/common/web/static/main-1d9b57a05a93155621b5.js.map
