Metadata-Version: 2.1
Name: cellxgene
Version: 1.3.0
Summary: Web application for exploration of large scale scRNA-seq datasets
Home-page: https://github.com/chanzuckerberg/cellxgene
Author: Chan Zuckerberg Initiative
Author-email: cellxgene@chanzuckerberg.com
License: MIT
Classifier: Framework :: Flask
Classifier: Intended Audience :: Science/Research
Classifier: License :: OSI Approved :: MIT License
Classifier: Natural Language :: English
Classifier: Operating System :: POSIX
Classifier: Operating System :: Unix
Classifier: Operating System :: MacOS :: MacOS X
Classifier: Programming Language :: JavaScript
Classifier: Programming Language :: Python :: 3
Classifier: Programming Language :: Python :: 3.10
Classifier: Programming Language :: Python :: 3.11
Classifier: Programming Language :: Python :: 3.12
Classifier: Programming Language :: Python :: 3 :: Only
Classifier: Topic :: Scientific/Engineering :: Bio-Informatics
Requires-Python: >=3.10
Requires-Dist: anndata>=0.8.0
Requires-Dist: boto3>=1.12.18
Requires-Dist: click>=7.1.2
Requires-Dist: Flask>=3.0.0
Requires-Dist: Flask-Compress>=1.4.0
Requires-Dist: Flask-Cors>=3.0.9
Requires-Dist: Flask-RESTful>=0.3.6
Requires-Dist: flask-server-timing>=0.1.2
Requires-Dist: flask-talisman>=0.7.0
Requires-Dist: flatbuffers==2.0.7
Requires-Dist: flatten-dict>=0.2.0
Requires-Dist: fsspec>0.8.0
Requires-Dist: gunicorn>=20.0.4
Requires-Dist: h5py>=3.0.0
Requires-Dist: numba>=0.60.0
Requires-Dist: numpy==2.0.1
Requires-Dist: packaging>=20.0
Requires-Dist: pandas>=2.2.2
Requires-Dist: PyYAML>=5.4
Requires-Dist: requests>=2.22.0
Requires-Dist: s3fs==0.4.2
Requires-Dist: scipy>=1.4
Requires-Dist: setuptools
Provides-Extra: prepare
Requires-Dist: python-igraph>=0.8; extra == "prepare"
Requires-Dist: louvain>=0.6; extra == "prepare"
Requires-Dist: scanpy; extra == "prepare"
Requires-Dist: umap-learn<0.5.0; extra == "prepare"
Provides-Extra: annotate
Requires-Dist: mlflow==2.16.0; extra == "annotate"
Requires-Dist: scanpy; extra == "annotate"
